paperfetcher/__init__.py
paperfetcher/apiclients.py
paperfetcher/content_negotiators.py
paperfetcher/datastructures.py
paperfetcher/exceptions.py
paperfetcher/handsearch.py
paperfetcher/parsers.py
paperfetcher/snowballsearch.py
paperfetcher-1.2.2.dist-info/LICENSE
paperfetcher-1.2.2.dist-info/METADATA
paperfetcher-1.2.2.dist-info/WHEEL
paperfetcher-1.2.2.dist-info/top_level.txt
paperfetcher-1.2.2.dist-info/RECORD
