Metadata-Version: 2.1
Name: paperfetcher
Version: 1.2.2
Summary: Python package to mine papers for systematic reviews.
Home-page: https://github.com/paperfetcher/paperfetcher
Author: Akash Pallath
Author-email: apallath@seas.upenn.edu
Requires-Python: >3.7
License-File: LICENSE
Requires-Dist: openpyxl
Requires-Dist: pandas
Requires-Dist: pytest
Requires-Dist: requests
Requires-Dist: rispy
Requires-Dist: stqdm
Requires-Dist: tqdm
